mindscheduler-1.0.2.dist-info/licenses/LICENSE
skill_scheduler/__init__.py
skill_scheduler/cli.py
skill_scheduler/core/__init__.py
skill_scheduler/core/dependency_manager.py
skill_scheduler/core/exceptions.py
skill_scheduler/core/executor.py
skill_scheduler/core/matcher.py
skill_scheduler/core/param_extractor.py
skill_scheduler/core/scheduler.py
skill_scheduler/core/skill.py
skill_scheduler/llm/__init__.py
skill_scheduler/llm/base.py
skill_scheduler/llm/openai.py
skill_scheduler/observability/__init__.py
skill_scheduler/observability/logging_config.py
skill_scheduler/observability/metrics.py
skill_scheduler/parsers/__init__.py
skill_scheduler/parsers/markdown_parser.py
skill_scheduler/prompts/__init__.py
skill_scheduler/utils/__init__.py
skill_scheduler/utils/config.py
skill_scheduler/utils/prompts.py
mindscheduler-1.0.2.dist-info/METADATA
mindscheduler-1.0.2.dist-info/WHEEL
mindscheduler-1.0.2.dist-info/entry_points.txt
mindscheduler-1.0.2.dist-info/top_level.txt
mindscheduler-1.0.2.dist-info/RECORD
