Metadata-Version: 2.4
Name: Mindscheduler
Version: 1.0.2
Summary: 一个轻量级、模块化的 LLM 增强型技能调度框架
Author-email: SkillScheduler Contributors <dev@skillscheduler.dev>
License: MIT
Project-URL: Homepage, https://github.com/skillscheduler/skillscheduler
Project-URL: Documentation, https://github.com/skillscheduler/skillscheduler#readme
Project-URL: Repository, https://github.com/skillscheduler/skillscheduler
Project-URL: Bug Tracker, https://github.com/skillscheduler/skillscheduler/issues
Keywords: automation,llm,skills,scheduling,markdown,agent
Classifier: Development Status :: 4 - Beta
Classifier: Intended Audience :: Developers
Classifier: License :: OSI Approved :: MIT License
Classifier: Programming Language :: Python :: 3
Classifier: Programming Language :: Python :: 3.8
Classifier: Programming Language :: Python :: 3.9
Classifier: Programming Language :: Python :: 3.10
Classifier: Programming Language :: Python :: 3.11
Classifier: Programming Language :: Python :: 3.12
Classifier: Topic :: Software Development :: Libraries :: Python Modules
Classifier: Topic :: Utilities
Requires-Python: >=3.8
License-File: LICENSE
Requires-Dist: python-frontmatter>=1.0.0
Requires-Dist: click>=8.0
Requires-Dist: openai>=1.0
Requires-Dist: packaging>=21.0
Provides-Extra: llm
Provides-Extra: embedding
Requires-Dist: sentence-transformers>=2.2; extra == "embedding"
Provides-Extra: prometheus
Requires-Dist: prometheus-client>=0.17; extra == "prometheus"
Provides-Extra: dev
Requires-Dist: pytest>=7.0; extra == "dev"
Requires-Dist: pytest-cov>=4.0; extra == "dev"
Requires-Dist: black>=23.0; extra == "dev"
Requires-Dist: mypy>=1.0; extra == "dev"
Provides-Extra: all
Requires-Dist: skillscheduler[embedding,prometheus]; extra == "all"
Dynamic: license-file
